regipy/__init__.py
regipy/cli.py
regipy/exceptions.py
regipy/hive_types.py
regipy/recovery.py
regipy/regdiff.py
regipy/registry.py
regipy/security_utils.py
regipy/structs.py
regipy/utils.py
regipy/plugins/__init__.py
regipy/plugins/plugin.py
regipy/plugins/plugin_template.py
regipy/plugins/utils.py
regipy/plugins/amcache/__init__.py
regipy/plugins/amcache/amcache.py
regipy/plugins/bcd/__init__.py
regipy/plugins/bcd/boot_entry_list.py
regipy/plugins/ntuser/__init__.py
regipy/plugins/ntuser/classes_installer.py
regipy/plugins/ntuser/installed_programs_ntuser.py
regipy/plugins/ntuser/persistence.py
regipy/plugins/ntuser/tsclient.py
regipy/plugins/ntuser/typed_urls.py
regipy/plugins/ntuser/user_assist.py
regipy/plugins/ntuser/word_wheel_query.py
regipy/plugins/sam/__init__.py
regipy/plugins/sam/local_sid.py
regipy/plugins/security/__init__.py
regipy/plugins/security/domain_sid.py
regipy/plugins/software/__init__.py
regipy/plugins/software/classes_installer.py
regipy/plugins/software/image_file_execution_options.py
regipy/plugins/software/installed_programs.py
regipy/plugins/software/last_logon.py
regipy/plugins/software/persistence.py
regipy/plugins/software/printdemon.py
regipy/plugins/software/profilelist.py
regipy/plugins/software/tracing.py
regipy/plugins/software/uac.py
regipy/plugins/system/__init__.py
regipy/plugins/system/active_controlset.py
regipy/plugins/system/bam.py
regipy/plugins/system/bootkey.py
regipy/plugins/system/computer_name.py
regipy/plugins/system/host_domain_name.py
regipy/plugins/system/routes.py
regipy/plugins/system/safeboot_configuration.py
regipy/plugins/system/services.py
regipy/plugins/system/shimcache.py
regipy/plugins/system/timezone_data.py
regipy/plugins/system/external/ShimCacheParser.py
regipy/plugins/system/external/__init__.py
regipy2-2.2.1.dist-info/LICENSE
regipy2-2.2.1.dist-info/METADATA
regipy2-2.2.1.dist-info/WHEEL
regipy2-2.2.1.dist-info/entry_points.txt
regipy2-2.2.1.dist-info/top_level.txt
regipy2-2.2.1.dist-info/RECORD
