Metadata-Version: 2.1
Name: regipy2
Version: 2.2.1
Summary: Python Registry Parser2 - This is a temporary advanced patched package, with relaxed dependency constraints. It is there only until upstream is updated. See https://github.com/nexB/regipy/ and https://github.com/mkorman90/regipy/pull/200
Home-page: https://github.com/mkorman90/regipy/
Author: Martin G. Korman
Author-email: martin@centauri.co.il
License: MIT
Keywords: Python,Python3,registry,windows registry,registry parser
Platform: UNKNOWN
Classifier: Development Status :: 5 - Production/Stable
Classifier: Intended Audience :: Developers
Classifier: Natural Language :: English
Classifier: License :: OSI Approved :: MIT License
Classifier: Programming Language :: Python
Classifier: Programming Language :: Python :: 3.6
Classifier: Programming Language :: Python :: 3.7
Classifier: Programming Language :: Python :: 3.8
Classifier: Programming Language :: Python :: 3.9
Classifier: Topic :: Software Development :: Libraries
Classifier: Topic :: Utilities
License-File: LICENSE
Requires-Dist: construct (>=2.10)
Requires-Dist: attrs (>=20)
Requires-Dist: inflection
Requires-Dist: pytz
Provides-Extra: cli
Requires-Dist: click (>=7.0.0) ; extra == 'cli'
Requires-Dist: tabulate ; extra == 'cli'
Provides-Extra: test
Requires-Dist: pytest ; extra == 'test'
Requires-Dist: pytest-flake8 ; extra == 'test'
